{
  "AF Vancouver": {
    "estado": "SIN_EVENTO",
    "fechas": [],
    "detalle": "Sin aperturas de registro pendientes detectadas",
    "ts": "2026-07-12T22:38:02.629899",
    "sesiones": []
  },
  "AF Victoria": {
    "estado": "SIN_EVENTO",
    "fechas": [],
    "detalle": "Sin aperturas de registro pendientes detectadas",
    "ts": "2026-07-12T22:38:10.585334",
    "sesiones": []
  },
  "AF Toronto": {
    "estado": "VERIFICAR",
    "fechas": [],
    "detalle": "Sin fechas detectadas — verificar manualmente",
    "ts": "2026-07-12T22:38:17.095345",
    "sesiones": []
  },
  "AF Calgary": {
    "estado": "VERIFICAR",
    "fechas": [],
    "detalle": "Sin señales claras — verificar manualmente",
    "ts": "2026-07-12T22:38:22.306728",
    "sesiones": []
  },
  "AF Edmonton": {
    "estado": "VERIFICAR",
    "fechas": [],
    "detalle": "Sin señales claras — verificar manualmente",
    "ts": "2026-07-12T22:38:27.091915",
    "sesiones": []
  },
  "Ashton Testing Services": {
    "estado": "BLOQUEADO",
    "fechas": [],
    "detalle": "Sitio bloqueó el acceso. Verificar manualmente.",
    "ts": "2026-07-12T22:38:32.053068",
    "sesiones": []
  },
  "GB Language Centre": {
    "estado": "VERIFICAR",
    "fechas": [],
    "detalle": "Página renderiza con JS; verificar manualmente en gblc.ca",
    "ts": "2026-07-12T22:38:50.321338",
    "sesiones": []
  }
}