{
  "AF Vancouver": {
    "estado": "SIN_EVENTO",
    "fechas": [],
    "detalle": "Sin aperturas de registro pendientes detectadas",
    "ts": "2026-07-09T19:22:11.563809",
    "sesiones": []
  },
  "AF Victoria": {
    "estado": "SIN_EVENTO",
    "fechas": [],
    "detalle": "Sin aperturas de registro pendientes detectadas",
    "ts": "2026-07-09T19:22:20.613016",
    "sesiones": []
  },
  "AF Toronto": {
    "estado": "VERIFICAR",
    "fechas": [],
    "detalle": "Sin fechas detectadas — verificar manualmente",
    "ts": "2026-07-09T19:22:26.626711",
    "sesiones": []
  },
  "AF Calgary": {
    "estado": "VERIFICAR",
    "fechas": [],
    "detalle": "Sin señales claras — verificar manualmente",
    "ts": "2026-07-09T19:22:31.337017",
    "sesiones": []
  },
  "AF Edmonton": {
    "estado": "VERIFICAR",
    "fechas": [],
    "detalle": "Sin señales claras — verificar manualmente",
    "ts": "2026-07-09T19:22:35.792462",
    "sesiones": []
  },
  "Ashton Testing Services": {
    "estado": "BLOQUEADO",
    "fechas": [],
    "detalle": "Sitio bloqueó el acceso. Verificar manualmente.",
    "ts": "2026-07-09T19:22:40.416118",
    "sesiones": []
  },
  "GB Language Centre": {
    "estado": "VERIFICAR",
    "fechas": [],
    "detalle": "Página renderiza con JS; verificar manualmente en gblc.ca",
    "ts": "2026-07-09T19:22:58.645994",
    "sesiones": []
  }
}