{
  "AF Vancouver": {
    "estado": "SIN_EVENTO",
    "fechas": [],
    "detalle": "Sin aperturas de registro pendientes detectadas",
    "ts": "2026-07-16T13:19:25.339299",
    "sesiones": []
  },
  "AF Victoria": {
    "estado": "SIN_EVENTO",
    "fechas": [],
    "detalle": "Sin aperturas de registro pendientes detectadas",
    "ts": "2026-07-16T13:19:33.829056",
    "sesiones": []
  },
  "AF Toronto": {
    "estado": "VERIFICAR",
    "fechas": [],
    "detalle": "Sin fechas detectadas — verificar manualmente",
    "ts": "2026-07-16T13:19:40.012455",
    "sesiones": []
  },
  "AF Calgary": {
    "estado": "VERIFICAR",
    "fechas": [],
    "detalle": "Sin señales claras — verificar manualmente",
    "ts": "2026-07-16T13:19:44.820209",
    "sesiones": []
  },
  "AF Edmonton": {
    "estado": "VERIFICAR",
    "fechas": [],
    "detalle": "Sin señales claras — verificar manualmente",
    "ts": "2026-07-16T13:19:49.432660",
    "sesiones": []
  },
  "Ashton Testing Services": {
    "estado": "BLOQUEADO",
    "fechas": [],
    "detalle": "Sitio bloqueó el acceso. Verificar manualmente.",
    "ts": "2026-07-16T13:19:54.106260",
    "sesiones": []
  },
  "GB Language Centre": {
    "estado": "VERIFICAR",
    "fechas": [],
    "detalle": "Página renderiza con JS; verificar manualmente en gblc.ca",
    "ts": "2026-07-16T13:20:12.494045",
    "sesiones": []
  }
}